vigentools/BaseRouter.py
vigentools/GlobalError.py
vigentools/InitConfig.py
vigentools/__init__.py
vigentools/py.typed
vigentools/res.py
vigentools/verify/__init__.py
vigentools/verify/bool.py
vigentools/verify/class.py
vigentools/verify/dict.py
vigentools/verify/empty.py
vigentools/verify/general.py
vigentools/verify/list.py
vigentools/verify/number.py
vigentools/verify/path.py
vigentools/verify/string.py
vigentools-0.0.3.dist-info/METADATA
vigentools-0.0.3.dist-info/WHEEL
vigentools-0.0.3.dist-info/RECORD
