Metadata-Version: 2.4
Name: vigentools
Version: 0.0.3
Summary: Add your description here
Requires-Python: >=3.8
Requires-Dist: fastapi>=0.115.12
Requires-Dist: jwt>=1.3.1
Requires-Dist: viconfig>=0.0.2
Requires-Dist: vidbcontrol>=0.1.0
Requires-Dist: vierror>=0.0.2
